nonebot_plugin_reborn/__init__.py
nonebot_plugin_reborn/chart.py
nonebot_plugin_reborn/data.py
nonebot_plugin_reborn-0.4.dist-info/LICENSE
nonebot_plugin_reborn-0.4.dist-info/METADATA
nonebot_plugin_reborn-0.4.dist-info/WHEEL
nonebot_plugin_reborn-0.4.dist-info/top_level.txt
nonebot_plugin_reborn-0.4.dist-info/RECORD
