Metadata-Version: 2.1
Name: nonebot-plugin-reborn
Version: 0.4
Summary: Reborn Simulator for Nonebot 2
Home-page: https://github.com/Aziteee/nonebot_plugin_reborn
Author: Azite
Author-email: aziteee@outlook.com
License: MIT License
Platform: all
Classifier: Operating System :: OS Independent
Classifier: License :: OSI Approved :: MIT License
Classifier: Programming Language :: Python :: 3
License-File: LICENSE
Requires-Dist: nonebot2 (>=2.0.0b3)
Requires-Dist: nonebot-adapter-onebot (>=2.0.0b1)
Requires-Dist: nonebot-plugin-htmlrender (>=0.0.4)
